pz_clean_menu/CleanMenu.py
pz_clean_menu/Console.py
pz_clean_menu/GeometricConsole.py
pz_clean_menu/__init__.py
pz_clean_menu-1.1.1.dist-info/METADATA
pz_clean_menu-1.1.1.dist-info/WHEEL
pz_clean_menu-1.1.1.dist-info/licenses/LICENSE
pz_clean_menu-1.1.1.dist-info/RECORD
