Metadata-Version: 2.4
Name: pz-clean-menu
Version: 1.1.1
Summary: A simple, elegant Python interactive menu system using the Rich library.
Project-URL: Homepage, https://github.com/poziel/clean-menu
Project-URL: Issues, https://github.com/poziel/clean-menu
Author-email: Alexandre Sauvé <alexandre.sauve.dev@gmail.com>
License-File: LICENSE
Classifier: License :: OSI Approved :: MIT License
Classifier: Operating System :: OS Independent
Classifier: Programming Language :: Python :: 3
Requires-Python: >=3.0
Requires-Dist: rich>=13.0.0
